{
  "撈": "这",
  "襪": "见",
  "颱": "过",
  "颪": "亚",
  "緞": "类",
  "顳": "经",
  "顯": "吗",
  "顋": "还",
  "醤": "现",
  "幀": "呢",
  "幟": "传",
  "竅": "闻",
  "顏": "说",
  "僑": "们",
  "譴": "爱",
  "簫": "样",
  "鵑": "龄",
  "鈑": "实",
  "蝿": "际",
  "憫": "话",
  "鉛": "啊",
  "贖": "晚",
  "憊": "乐",
  "綴": "园",
  "繹": "时",
  "頸": "变",
  "韲": "袭",
  "絞": "击",
  "韈": "对",
  "詮": "种",
  "韆": "语",
  "鞴": "懂",
  "鞐": "远",
  "羈": "剧",
  "錐": "减",
  "梱": "夺",
  "鞦": "乡",
  "誡": "结",
  "頒": "队",
  "諦": "伙",
  "翹": "东",
  "鞨": "为",
  "澆": "吧",
  "獰": "热",
  "熾": "么",
  "漣": "嗯",
  "聾": "动",
  "絆": "细",
  "瀉": "步",
  "袞": "刚",
  "訶": "应",
  "鞜": "该",
  "鞆": "难",
  "懴": "终",
  "靺": "馆",
  "鞁": "觉",
  "靹": "呜",
  "瀘": "喵",
  "靱": "～",
  "憚": "跑",
  "暉": "—",
  "驤": "你",
  "撓": "错",
  "諭": "呐",
  "靤": "咦",
  "櫓": "恶",
  "鰐": "伤",
  "靜": "脑",
  "閔": "让",
  "轍": "赛",
  "瓏": "呃",
  "諌": "总",
  "靉": "尔",
  "蝦": "给",
  "靈": "兴",
  "蹌": "黑",
  "靆": "咪",
  "霤": "毕",
  "逕": "宠",
  "霙": "别",
  "兌": "欢",
  "輓": "喂",
  "雜": "试",
  "訟": "劲",
  "襍": "挠",
  "隸": "偷",
  "靭": "搞",
  "鬢": "咿",
  "隱": "兰",
  "闕": "叹",
  "賄": "绪",
  "嶄": "稳",
  "軾": "纽",
  "險": "啪",
  "陦": "嗒",
  "陝": "哪",
  "鱗": "场",
  "陞": "长",
  "鈍": "哼",
  "滸": "头",
  "嘖": "聪",
  "陏": "带",
  "阯": "诶",
  "韃": "问",
  "鰲": "适",
  "阨": "树",
  "闢": "识",
  "關": "飞",
  "闍": "领",
  "馴": "轻",
  "濶": "啥",
  "閧": "马",
  "頷": "迈",
  "躊": "鲁",
  "閠": "开",
  "婁": "记",
  "鈬": "词",
  "鉉": "嘿",
  "閙": "间",
  "鴿": "鸡",
  "閖": "嘻",
  "閊": "啦",
  "渦": "哟",
  "懾": "边",
  "閇": "哎",
  "钁": "厉",
  "駅": "奖",
  "薐": "噔",
  "籬": "诺",
  "蛍": "谢",
  "輾": "扬",
  "墾": "贵",
  "鑽": "询",
  "謨": "闹",
  "顱": "腾",
  "鑵": "赚",
  "釟": "红",
  "儼": "复",
  "檸": "骂",
  "桟": "办",
  "絹": "谁",
  "謗": "帅",
  "竃": "敌",
  "鈩": "顺",
  "詣": "驯",
  "倹": "兽",
  "鑪": "师",
  "柵": "佬",
  "饅": "挡",
  "轄": "剑",
  "棗": "论",
  "鑢": "绝",
  "嫋": "谅",
  "鑛": "误",
  "鑄": "处",
  "贅": "嚣",
  "鑒": "张",
  "鑁": "罗",
  "鐡": "饿",
  "輳": "鱼",
  "闌": "饶",
  "鐵": "钓",
  "癆": "贪",
  "緬": "风",
  "鐶": "车",
  "鹸": "饭",
  "輒": "预",
  "馭": "进",
  "韜": "躲",
  "喞": "员",
  "鐇": "闯",
  "鐓": "关",
  "畝": "讨",
  "鐔": "厌",
  "鐚": "酱",
  "繚": "她",
  "絳": "饼",
  "僥": "扭",
  "誨": "嘁",
  "檻": "养",
  "褻": "换",
  "饋": "锐",
  "塢": "隐",
  "鏝": "显",
  "紂": "发",
  "噸": "险",
  "鏥": "卡",
  "鎹": "题",
  "涜": "噜",
  "諜": "蹭",
  "鋸": "战",
  "鎔": "眯",
  "鄒": "凑",
  "訛": "虽",
  "鐸": "噗",
  "薔": "钻",
  "瀏": "单",
  "鐙": "侦",
  "攅": "嚯",
  "紡": "娇",
  "鎭": "糕",
  "鍖": "赶",
  "雋": "紧",
  "惻": "灭",
  "紜": "吓",
  "鍮": "确",
  "鍼": "认",
  "鍠": "咕",
  "鍜": "骑",
  "緯": "踢",
  "錻": "邻",
  "楡": "烦",
  "瘡": "满",
  "讒": "门",
  "鑼": "响",
  "緝": "诉",
  "躡": "许",
  "錵": "瞒",
  "錺": "捡",
  "釁": "扔",
  "綏": "嘞",
  "矚": "验",
  "錣": "释",
  "駒": "俏",
  "錢": "闲",
  "鍄": "沉",
  "蠱": "骗",
  "鋺": "侣",
  "錏": "谓",
  "鋩": "掐",
  "銛": "疯",
  "獎": "抚",
  "締": "悬",
  "癲": "缝",
  "瀝": "颤",
  "鉐": "闪",
  "儂": "碰",
  "鴎": "软",
  "鋤": "胀",
  "銕": "绵",
  "鉈": "仅",
  "鉅": "两",
  "參": "罢",
  "襖": "调",
  "詰": "傻",
  "釿": "节",
  "貽": "离",
  "靂": "缓",
  "燼": "极",
  "釶": "咚",
  "葦": "俩",
  "嗇": "嘟",
  "繭": "晕",
  "頡": "顾",
  "簒": "费",
  "釼": "摇",
  "錮": "脸",
  "蛻": "阴",
  "釛": "卧",
  "釡": "强",
  "釖": "您",
  "餌": "药",
  "鉗": "烧",
  "釐": "举",
  "闔": "怀",
  "詁": "暂",
  "綾": "够",
  "鯨": "呛",
  "釋": "约",
  "醯": "哒",
  "醫": "产",
  "醂": "坟",
  "謁": "权",
  "嫻": "拼",
  "酳": "仿",
  "酘": "忆",
  "軼": "环",
  "騁": "达",
  "酖": "蹦",
  "愴": "贴",
  "髏": "妈",
  "澗": "炼",
  "邉": "坚",
  "遲": "请",
  "腎": "级",
  "隨": "泽",
  "氈": "滨",
  "巓": "习",
  "璽": "惯",
  "鉢": "嘎",
  "轅": "嘣",
  "絢": "卖",
  "飆": "霉",
  "遶": "斩",
  "賍": "娅",
  "漬": "惊",
  "遯": "扯",
  "遞": "电",
  "諺": "盯",
  "誹": "彻",
  "騾": "龙",
  "蟄": "虾",
  "縹": "帮",
  "遖": "喏",
  "遉": "绍",
  "逎": "·",
  "逹": "兹",
  "癩": "杀",
  "藹": "滚",
  "逧": "训",
  "藾": "顿",
  "窯": "镇",
  "迴": "织",
  "邇": "遗",
  "鐺": "皱",
  "磽": "扑",
  "殱": "丧",
  "瀕": "赢",
  "迯": "输",
  "迚": "丢",
  "辷": "责",
  "駢": "义",
  "辭": "伟",
  "轣": "败",
  "雛": "墙",
  "轢": "洁",
  "佇": "懒",
  "謔": "锻",
  "緲": "简",
  "滌": "备",
  "轜": "阵",
  "銹": "骚",
  "轗": "荣",
  "轉": "纪",
  "轌": "饱",
  "鯊": "啧",
  "諳": "录",
  "輹": "鸟",
  "諄": "护",
  "磯": "务",
  "靄": "岁",
  "颯": "术",
  "謫": "值",
  "渙": "驶",
  "輛": "疗",
  "輙": "压",
  "軣": "躺",
  "軈": "诱",
  "嶼": "吞",
  "賂": "溅",
  "軅": "摆",
  "躾": "纱",
  "曖": "颊",
  "軆": "奶",
  "鸞": "练",
  "軋": "顶",
  "緋": "肤",
  "躰": "丽",
  "貳": "渐",
  "鏗": "哑",
  "躙": "杂",
  "躔": "阳",
  "綸": "噢",
  "躄": "哧",
  "鸚": "啰",
  "閘": "轮",
  "蹠": "胜",
  "濾": "唰",
  "蹤": "视",
  "搾": "线",
  "蹐": "砸",
  "踴": "唉",
  "魘": "买",
  "踰": "资",
  "慟": "狱",
  "唄": "铠",
  "踐": "每",
  "梟": "榈",
  "貯": "岛",
  "跿": "弹",
  "踈": "挣",
  "纓": "议",
  "跼": "扰",
  "赱": "吵",
  "贔": "态",
  "贓": "连",
  "贐": "续",
  "贊": "辩",
  "匱": "标",
  "膾": "瞄",
  "賻": "塌",
  "輟": "负",
  "篩": "谎",
  "錠": "查",
  "歟": "净",
  "賤": "亏",
  "貮": "朵",
  "撻": "灵",
  "飼": "戏",
  "戝": "阱",
  "膿": "盘",
  "釧": "华",
  "豼": "汤",
  "貎": "钱",
  "貍": "另",
  "霑": "嘭",
  "詼": "扫",
  "纜": "顽",
  "霽": "颜",
  "餃": "购",
  "殯": "运",
  "塋": "壶",
  "閂": "荡",
  "鶚": "赔",
  "錨": "书",
  "繽": "亲",
  "鏘": "爸",
  "豬": "帕",
  "隕": "铁",
  "豎": "联",
  "谺": "俱",
  "讙": "组",
  "閹": "须",
  "痺": "窝",
  "讌": "笼",
  "讀": "冯",
  "譽": "积",
  "譯": "鸣",
  "緘": "逛",
  "譟": "规",
  "鹵": "鳕",
  "餉": "吱",
  "葷": "肿",
  "譖": "艺",
  "輻": "计",
  "證": "划",
  "燉": "咻",
  "譌": "胁",
  "謚": "撑",
  "譁": "踹",
  "謠": "拖",
  "鵡": "烤",
  "諡": "浑",
  "謌": "宽",
  "鐐": "德",
  "諠": "蜡",
  "紺": "烛",
  "諫": "缘",
  "諚": "转",
  "誂": "焰",
  "巒": "纸",
  "觸": "异",
  "謐": "牺",
  "靫": "卫",
  "觧": "尝",
  "觝": "窥",
  "觀": "闭",
  "蹣": "渴",
  "覽": "呸",
  "蝟": "粪",
  "簍": "跷",
  "覺": "咙",
  "覩": "丝",
  "覊": "绸",
  "覈": "缠",
  "襾": "绕",
  "襷": "丰",
  "躪": "挤",
  "襴": "绷",
  "鷲": "艳",
  "慫": "飘",
  "襭": "拧",
  "懣": "搐",
  "囁": "痉",
  "觴": "挛",
  "哢": "讶",
  "褝": "额",
  "牘": "详",
  "襌": "夹",
  "褞": "沟",
  "鯉": "撸",
  "褌": "浓",
  "褄": "质",
  "裲": "圆",
  "裝": "润",
  "裄": "翘",
  "礫": "伞",
  "攣": "势",
  "謳": "挥",
  "袿": "叽",
  "軻": "浊",
  "袰": "喷",
  "袮": "嗝",
  "袗": "脏",
  "鎌": "恼",
  "諂": "锁",
  "詆": "份",
  "袵": "桌",
  "衵": "帘",
  "衞": "报",
  "欒": "晾",
  "衒": "裤",
  "餒": "铺",
  "驥": "趟",
  "衂": "较",
  "驍": "蹋",
  "衄": "丫",
  "蠻": "爹",
  "餡": "佣",
  "蠧": "银",
  "齪": "胧",
  "餞": "偎",
  "蠶": "牵",
  "蠑": "贯",
  "蠎": "营",
  "齷": "烂",
  "蟷": "咱",
  "蠍": "穷",
  "蠏": "诛",
  "潁": "揍",
  "蟲": "砍",
  "蟇": "窸",
  "蟐": "窣",
  "螢": "拥",
  "蠅": "唤",
  "囈": "搔",
  "蝪": "搅",
  "蝨": "迟",
  "嶇": "钝",
  "蜑": "饰",
  "閭": "绣",
  "蛯": "摔",
  "蛬": "逊",
  "蠣": "缩",
  "靦": "舔",
  "蚰": "龟",
  "號": "侧",
  "乕": "辉",
  "虍": "奋",
  "蘰": "嘬",
  "蘆": "啵",
  "鷺": "刘",
  "蘋": "唧",
  "蘓": "捆",
  "藥": "绑",
  "諛": "踩",
  "薹": "谒",
  "顰": "诚",
  "痙": "绞",
  "蕷": "绳",
  "藪": "腻",
  "鏤": "块",
  "薑": "衅",
  "薀": "宫",
  "臍": "执",
  "蝸": "锤",
  "蕋": "团",
  "蘂": "蓝",
  "蕣": "圣",
  "褸": "肮",
  "蕀": "咣",
  "蔔": "贸",
  "謾": "评",
  "龕": "虑",
  "慂": "导",
  "溏": "韧",
  "蔕": "滩",
  "蔟": "轰",
  "騫": "阁",
  "鴣": "拽",
  "蔘": "胳",
  "襤": "狈",
  "蓆": "赎",
  "嫗": "喔",
  "蓚": "鸽",
  "噛": "惩",
  "蒻": "罚",
  "欖": "跄",
  "濘": "亿",
  "蓙": "嗖",
  "蒟": "继",
  "煬": "颗",
  "皚": "姣",
  "葢": "纠",
  "輦": "纷",
  "葹": "谋",
  "驪": "姬",
  "鷓": "讲",
  "葯": "闺",
  "飩": "糙",
  "萬": "寻",
  "轆": "砾",
  "葮": "雾",
  "蒭": "咔",
  "蒄": "嚓",
  "曁": "赌",
  "蕚": "获",
  "綰": "丛",
  "銓": "妇",
  "鉞": "庆",
  "儷": "趴",
  "曇": "宾",
  "駄": "访",
  "贍": "颈",
  "萪": "军",
  "菻": "载",
  "儻": "凯",
  "駟": "优",
  "躋": "贺",
  "蔆": "增",
  "萠": "侄",
  "萢": "统",
  "菷": "渗",
  "崢": "辈",
  "菎": "炽",
  "枠": "锋",
  "菫": "眨",
  "萓": "哗",
  "菴": "泼",
  "贄": "抢",
  "荵": "盔",
  "荳": "赖",
  "鵠": "铜",
  "讖": "呲",
  "莵": "竞",
  "嚀": "叠",
  "嬪": "揭",
  "莊": "拨",
  "莇": "贬",
  "鐫": "职",
  "茣": "货",
  "莖": "愤",
  "莟": "选",
  "莚": "呗",
  "閏": "疙",
  "脛": "瘩",
  "誥": "垫",
  "茘": "检",
  "譎": "镜",
  "荅": "舰",
  "茖": "贫",
  "苙": "雳",
  "茆": "笔",
  "嚶": "测",
  "苺": "辫",
  "襠": "临",
  "苳": "泞",
  "艸": "呕",
  "鯤": "钢",
  "艷": "惭",
  "漑": "婶",
  "舮": "观",
  "薈": "众",
  "殤": "诅",
  "擯": "赐",
  "艪": "咧",
  "艨": "锈",
  "瞼": "悯",
  "覦": "绊",
  "艢": "噩",
  "芻": "咖",
  "艟": "喱",
  "艚": "绿",
  "犢": "齐",
  "艝": "瞧",
  "綬": "垃",
  "鄲": "圾",
  "艀": "签",
  "舩": "苍",
  "舖": "蝇",
  "鴇": "飕",
  "歿": "订",
  "舊": "劳",
  "與": "废",
  "鸛": "谈",
  "檳": "耍",
  "臺": "项",
  "臟": "忧",
  "覬": "陨",
  "飭": "审",
  "塹": "饮",
  "臈": "仪",
  "臙": "羁",
  "臑": "专",
  "膽": "阂",
  "膸": "综",
  "膵": "倾",
  "慍": "妞",
  "櫚": "坠",
  "膰": "颇",
  "膓": "证",
  "賁": "贱",
  "羶": "颂",
  "鳶": "卢",
  "腟": "诞",
  "膣": "澜",
  "膤": "畅",
  "膕": "础",
  "膃": "睬",
  "諢": "谜",
  "腦": "归",
  "脣": "历",
  "脩": "贤",
  "肬": "谐",
  "冐": "轨",
  "肭": "妒",
  "肅": "馁",
  "聽": "读",
  "聹": "构",
  "聰": "业",
  "捫": "编",
  "聲": "键",
  "聨": "则",
  "聢": "绰",
  "鍍": "蟑",
  "顎": "浆",
  "聟": "骄",
  "耡": "狮",
  "鷦": "鲤",
  "靨": "债",
  "飜": "玷",
  "翆": "污",
  "譱": "谊",
  "羮": "鹅",
  "覲": "盐",
  "羣": "渍",
  "羇": "补",
  "羃": "榄",
  "銖": "鳖",
  "羂": "闷",
  "罸": "嘀",
  "輕": "馅",
  "罧": "纯",
  "罌": "驾",
  "薊": "炖",
  "罠": "鹑",
  "罎": "饺",
  "鮟": "济",
  "纎": "枣",
  "轡": "辅",
  "纖": "瘫",
  "纔": "图",
  "纐": "烁",
  "纒": "莹",
  "鶻": "捂",
  "續": "眶",
  "繿": "甩",
  "緕": "绘",
  "纃": "涩",
  "鑞": "涂",
  "繻": "瘪",
  "繼": "脖",
  "繩": "呦",
  "鈿": "旷",
  "繪": "耸",
  "繙": "汉",
  "繖": "纤",
  "繧": "赋",
  "鯀": "沦",
  "縺": "溃",
  "繦": "跃",
  "縱": "谚",
  "縒": "羡",
  "縡": "严",
  "縣": "觑",
  "縅": "蕴",
  "誚": "侥",
  "緻": "颠",
  "緤": "纹",
  "颶": "贼",
  "綟": "瞌",
  "緜": "贝",
  "殞": "壳",
  "綯": "针",
  "總": "销",
  "綫": "围",
  "綵": "铸",
  "綛": "阔",
  "絽": "绯",
  "襃": "衬",
  "徠": "厅",
  "經": "赏",
  "絣": "枪",
  "饗": "违",
  "絏": "毁",
  "絎": "捣",
  "縉": "搪",
  "絖": "惕",
  "紵": "码",
  "紮": "凿",
  "絅": "厢",
  "詬": "币",
  "糺": "驳",
  "鳬": "钟",
  "橢": "宁",
  "糴": "镀",
  "縊": "涤",
  "糒": "钩",
  "糘": "嗡",
  "鶩": "潇",
  "糂": "赞",
  "鍬": "诡",
  "糀": "篮",
  "粨": "嗵",
  "粡": "递",
  "粫": "睁",
  "粢": "谦",
  "粭": "嗦",
  "粐": "贷",
  "浹": "挖",
  "粃": "纳",
  "籵": "嗞",
  "曄": "偿",
  "訐": "爷",
  "籖": "监",
  "籤": "茬",
  "籟": "财",
  "籘": "诈",
  "軫": "垮",
  "奩": "谱",
  "籐": "喻",
  "籏": "户",
  "籔": "晓",
  "簷": "掰",
  "篶": "钧",
  "鴕": "瘾",
  "簗": "裆",
  "簓": "呿",
  "簀": "澈",
  "蘚": "账",
  "殫": "枫",
  "籠": "厕",
  "儕": "诽",
  "愾": "谤",
  "簔": "启",
  "簑": "仃",
  "縟": "坨",
  "篏": "艰",
  "箙": "创",
  "幃": "蹩",
  "箏": "亵",
  "箒": "渎",
  "箚": "歧",
  "箟": "绩",
  "鑾": "惫",
  "箘": "荫",
  "筬": "择",
  "獪": "层",
  "筰": "挚",
  "筴": "贡",
  "筥": "螃",
  "筅": "嘈",
  "饌": "齿",
  "筍": "讽",
  "筺": "锵",
  "騅": "瞪",
  "笶": "啤",
  "笵": "锦",
  "笘": "飙",
  "笂": "鸥",
  "甌": "诸",
  "竢": "犷",
  "竡": "维",
  "竝": "焕",
  "竚": "陡",
  "竓": "坛",
  "竏": "谧",
  "謄": "秽",
  "訖": "阶",
  "誑": "频",
  "竍": "涨",
  "竊": "嚷",
  "窰": "妆",
  "儔": "损",
  "竈": "蚂",
  "穽": "蚁",
  "龝": "岂",
  "穩": "协",
  "椏": "擞",
  "穉": "谬",
  "穃": "扒",
  "稾": "哐",
  "稱": "皂",
  "稟": "灿",
  "稙": "聋",
  "稘": "搂",
  "鑠": "跺",
  "顴": "饵",
  "秡": "鳍",
  "潯": "祸",
  "槞": "钮",
  "秬": "谣",
  "禮": "农",
  "禪": "巢",
  "齋": "鹰",
  "繝": "驰",
  "贋": "啷",
  "繕": "鲜",
  "禝": "虏",
  "瘧": "骷",
  "縵": "髅",
  "祿": "垄",
  "祕": "嚎",
  "礙": "瘦",
  "篋": "贞",
  "礑": "妩",
  "賃": "络",
  "讎": "竖",
  "礒": "诗",
  "礇": "纵",
  "磚": "课",
  "奐": "讪",
  "儺": "帐"
}