[
  {
    "index": 1,
    "name": "有紗",
    "pre_jp": "「フォローしてくれてるの？」",
    "post_jp": "フォローしてくれてるの？",
    "pre_zh": "你在安慰我吗？",
    "proofread_zh": "",
    "trans_by": "sakura-009",
    "proofread_by": "",
    "post_zh_preview": "「你在安慰我吗？」"
  },
  {
    "index": 2,
    "name": "透磨",
    "pre_jp": "「へ？　……ま、まぁ、そういうことだ。だから気にするな」",
    "post_jp": "へ？　……ま、まぁ、そういうことだ。だから気にするな",
    "pre_zh": "哎？……算、算是吧，就是这么回事。所以你别在意了",
    "proofread_zh": "",
    "trans_by": "sakura-009",
    "proofread_by": "",
    "post_zh_preview": "「哎？……算、算是吧，就是这么回事。所以你别在意了」"
  },
  {
    "index": 3,
    "name": "有紗",
    "pre_jp": "「お兄ちゃん、たまには優しいのね」",
    "post_jp": "お兄ちゃん、たまには優しいのね",
    "pre_zh": "哥哥，你偶尔也会很温柔呢",
    "proofread_zh": "",
    "trans_by": "sakura-009",
    "proofread_by": "",
    "post_zh_preview": "「哥哥，你偶尔也会很温柔呢」"
  },
  {
    "index": 4,
    "name": "透磨",
    "pre_jp": "「た、たまには！？」",
    "post_jp": "た、たまには！？",
    "pre_zh": "偶、偶尔！？",
    "proofread_zh": "",
    "trans_by": "sakura-009",
    "proofread_by": "",
    "post_zh_preview": "「偶、偶尔！？」"
  },
  {
    "index": 5,
    "name": "有紗",
    "pre_jp": "「いつもはなんか暗いし、あんまり喋らないし、何をしてるのかよく分からないところあるじゃない」",
    "post_jp": "いつもはなんか暗いし、あんまり喋らないし、何をしてるのかよく分からないところあるじゃない",
    "pre_zh": "你平时总是很阴沉，也不怎么说话，有时候甚至不知道你在做什么",
    "proofread_zh": "",
    "trans_by": "sakura-009",
    "proofread_by": "",
    "post_zh_preview": "「你平时总是很阴沉，也不怎么说话，有时候甚至不知道你在做什么」"
  },
  {
    "index": 6,
    "name": "透磨",
    "pre_jp": "「うぐ……」",
    "post_jp": "うぐ……",
    "pre_zh": "唔……",
    "proofread_zh": "",
    "trans_by": "sakura-009",
    "proofread_by": "",
    "post_zh_preview": "「唔……」"
  },
  {
    "index": 7,
    "name": "有紗",
    "pre_jp": "「でも、私が学園を休んだ時はちゃんとご飯作ってくれたりするし、悩みごとにもちゃんとフォローしてくれてるんだなって」",
    "post_jp": "でも、私が学園を休んだ時はちゃんとご飯作ってくれたりするし、悩みごとにもちゃんとフォローしてくれてるんだなって",
    "pre_zh": "但是，我请假没去上学的时候，你会好好地给我做饭，也会认真地听我倾诉烦恼",
    "proofread_zh": "",
    "trans_by": "sakura-009",
    "proofread_by": "",
    "post_zh_preview": "「但是，我请假没去上学的时候，你会好好地给我做饭，也会认真地听我倾诉烦恼」"
  },
  {
    "index": 8,
    "name": "",
    "pre_jp": "有紗は、自分が見ようとしていなかっただけで、実際は周りにもっと人の想いがあることに気づく。",
    "post_jp": "有紗は、自分が見ようとしていなかっただけで、実際は周りにもっと人の想いがあることに気づく。",
    "pre_zh": "有纱终于意识到，只是自己没有去关注，其实周围的人对她也抱有各种各样的感情。",
    "proofread_zh": "",
    "trans_by": "sakura-009",
    "proofread_by": "",
    "post_zh_preview": "有纱终于意识到，只是自己没有去关注，其实周围的人对她也抱有各种各样的感情。"
  },
  {
    "index": 9,
    "name": "",
    "pre_jp": "そう感じると、透磨のことももっと見直してもいい気がしてきた。",
    "post_jp": "そう感じると、透磨のことももっと見直してもいい気がしてきた。",
    "pre_zh": "有纱这么想，感觉可以对透磨刮目相看了。",
    "proofread_zh": "",
    "trans_by": "sakura-009",
    "proofread_by": "",
    "post_zh_preview": "有纱这么想，感觉可以对透磨刮目相看了。"
  },
  {
    "index": 10,
    "name": "透磨",
    "pre_jp": "「ま、なんだ。早く食え」",
    "post_jp": "ま、なんだ。早く食え",
    "pre_zh": "好了，快吃吧",
    "proofread_zh": "",
    "trans_by": "sakura-009",
    "proofread_by": "",
    "post_zh_preview": "「好了，快吃吧」"
  },
  {
    "index": 11,
    "name": "有紗",
    "pre_jp": "「うん、ありがとう、お兄ちゃん」",
    "post_jp": "うん、ありがとう、お兄ちゃん",
    "pre_zh": "嗯，谢谢哥哥",
    "proofread_zh": "",
    "trans_by": "sakura-009",
    "proofread_by": "",
    "post_zh_preview": "「嗯，谢谢哥哥」"
  },
  {
    "index": 12,
    "name": "",
    "pre_jp": "透磨はふんと鼻を鳴らし、シチューをほおばる。",
    "post_jp": "透磨はふんと鼻を鳴らし、シチューをほおばる。",
    "pre_zh": "透磨哼了一声，开始大口吃炖菜。",
    "proofread_zh": "",
    "trans_by": "sakura-009",
    "proofread_by": "",
    "post_zh_preview": "透磨哼了一声，开始大口吃炖菜。"
  },
  {
    "index": 13,
    "name": "",
    "pre_jp": "心なしか、透磨が照れているように見えた。",
    "post_jp": "心なしか、透磨が照れているように見えた。",
    "pre_zh": "不知是不是错觉，透磨看起来似乎在害羞。",
    "proofread_zh": "",
    "trans_by": "sakura-009",
    "proofread_by": "",
    "post_zh_preview": "不知是不是错觉，透磨看起来似乎在害羞。"
  }
]