[
  {
    "index": 1,
    "name": "優花",
    "pre_jp": "「それでさー、決着がつくかと思ったらまた来週！　だもん。もう、すごくいらいらするんだよね」",
    "post_jp": "それでさー、決着がつくかと思ったらまた来週！　だもん。もう、すごくいらいらするんだよね",
    "pre_zh": "然后啊，以为要分出胜负了，结果下周再见！真是让人急得要命",
    "proofread_zh": "",
    "trans_by": "sakura-009",
    "proofread_by": "",
    "post_zh_preview": "「然后啊，以为要分出胜负了，结果下周再见！真是让人急得要命」"
  },
  {
    "index": 2,
    "name": "美鈴",
    "pre_jp": "「ふふ。優花ちゃん、本当に毎週楽しみにしてるんだね」",
    "post_jp": "ふふ。優花ちゃん、本当に毎週楽しみにしてるんだね",
    "pre_zh": "呵呵，优花，你真的每周都很期待呢",
    "proofread_zh": "",
    "trans_by": "sakura-009",
    "proofread_by": "",
    "post_zh_preview": "「呵呵，优花，你真的每周都很期待呢」"
  },
  {
    "index": 3,
    "name": "優花",
    "pre_jp": "「面白いんだって。有紗も今度見てみなよ」",
    "post_jp": "面白いんだって。有紗も今度見てみなよ",
    "pre_zh": "因为很有趣嘛。有纱下次也看看吧",
    "proofread_zh": "",
    "trans_by": "sakura-009",
    "proofread_by": "",
    "post_zh_preview": "「因为很有趣嘛。有纱下次也看看吧」"
  },
  {
    "index": 4,
    "name": "有紗",
    "pre_jp": "「うーん、そういうのって、途中から見ても分からないと思うんだけど」",
    "post_jp": "うーん、そういうのって、途中から見ても分からないと思うんだけど",
    "pre_zh": "唔，这种东西，中途开始看的话应该会看不懂吧",
    "proofread_zh": "",
    "trans_by": "sakura-009",
    "proofread_by": "",
    "post_zh_preview": "「唔，这种东西，中途开始看的话应该会看不懂吧」"
  },
  {
    "index": 5,
    "name": "優花",
    "pre_jp": "「大丈夫、あたしが原作全部貸してあげる」",
    "post_jp": "大丈夫、あたしが原作全部貸してあげる",
    "pre_zh": "没事，我把原作全部借给你",
    "proofread_zh": "",
    "trans_by": "sakura-009",
    "proofread_by": "",
    "post_zh_preview": "「没事，我把原作全部借给你」"
  },
  {
    "index": 6,
    "name": "",
    "pre_jp": "優花が昨日のアニメを熱っぽく語るのを、有紗は自然と耳を傾けていた。",
    "post_jp": "優花が昨日のアニメを熱っぽく語るのを、有紗は自然と耳を傾けていた。",
    "pre_zh": "优花热情地谈论着昨天的动画，有纱自然地倾听着。",
    "proofread_zh": "",
    "trans_by": "sakura-009",
    "proofread_by": "",
    "post_zh_preview": "优花热情地谈论着昨天的动画，有纱自然地倾听着。"
  },
  {
    "index": 7,
    "name": "",
    "pre_jp": "今までは興味がないと聞く気も起こらなかったのに、なんとなく聞いてしまう。",
    "post_jp": "今までは興味がないと聞く気も起こらなかったのに、なんとなく聞いてしまう。",
    "pre_zh": "以前明明因为没有兴趣而不想听，现在却不知不觉地听了起来。",
    "proofread_zh": "",
    "trans_by": "sakura-009",
    "proofread_by": "",
    "post_zh_preview": "以前明明因为没有兴趣而不想听，现在却不知不觉地听了起来。"
  },
  {
    "index": 8,
    "name": "",
    "pre_jp": "その内容についていけなかったとしても、こうして優花達と話をしているだけでも楽しかった。",
    "post_jp": "その内容についていけなかったとしても、こうして優花達と話をしているだけでも楽しかった。",
    "pre_zh": "就算跟不上内容，光是像这样和优花她们聊天就很开心了。",
    "proofread_zh": "",
    "trans_by": "sakura-009",
    "proofread_by": "",
    "post_zh_preview": "就算跟不上内容，光是像这样和优花她们聊天就很开心了。"
  },
  {
    "index": 9,
    "name": "？？？",
    "pre_jp": "「ほら、ぐずぐずしてないでさっさと歩く」",
    "post_jp": "ほら、ぐずぐずしてないでさっさと歩く",
    "pre_zh": "好了，别磨磨蹭蹭的，快走吧",
    "proofread_zh": "",
    "trans_by": "sakura-009",
    "proofread_by": "",
    "post_zh_preview": "「好了，别磨磨蹭蹭的，快走吧」"
  },
  {
    "index": 10,
    "name": "？？？",
    "pre_jp": "「はい……あぅっ！」",
    "post_jp": "はい……あぅっ！",
    "pre_zh": "好的……啊呜！",
    "proofread_zh": "",
    "trans_by": "sakura-009",
    "proofread_by": "",
    "post_zh_preview": "「好的……啊呜！」"
  },
  {
    "index": 11,
    "name": "",
    "pre_jp": "気弱そうな少女がつまづいてその場に倒れる。",
    "post_jp": "気弱そうな少女がつまづいてその場に倒れる。",
    "pre_zh": "怯弱的少女绊了一下，摔倒在地。",
    "proofread_zh": "",
    "trans_by": "sakura-009",
    "proofread_by": "",
    "post_zh_preview": "怯弱的少女绊了一下，摔倒在地。"
  },
  {
    "index": 12,
    "name": "",
    "pre_jp": "有紗の視線はついその光景に向いていた。",
    "post_jp": "有紗の視線はついその光景に向いていた。",
    "pre_zh": "有纱的视线不由得转向了那边。",
    "proofread_zh": "",
    "trans_by": "sakura-009",
    "proofread_by": "",
    "post_zh_preview": "有纱的视线不由得转向了那边。"
  },
  {
    "index": 13,
    "name": "？？？",
    "pre_jp": "「まったく、何やってんのよ。ほんと、トロいんだから……」",
    "post_jp": "まったく、何やってんのよ。ほんと、トロいんだから……",
    "pre_zh": "真是的，你在干什么啊。你这人真是迟钝……",
    "proofread_zh": "",
    "trans_by": "sakura-009",
    "proofread_by": "",
    "post_zh_preview": "「真是的，你在干什么啊。你这人真是迟钝……」"
  },
  {
    "index": 14,
    "name": "？？？",
    "pre_jp": "「ごめんなさい……」",
    "post_jp": "ごめんなさい……",
    "pre_zh": "对不起……",
    "proofread_zh": "",
    "trans_by": "sakura-009",
    "proofread_by": "",
    "post_zh_preview": "「对不起……」"
  },
  {
    "index": 15,
    "name": "？？？",
    "pre_jp": "「ほら、さっさと立ちなさいよ」",
    "post_jp": "ほら、さっさと立ちなさいよ",
    "pre_zh": "好了，快站起来吧",
    "proofread_zh": "",
    "trans_by": "sakura-009",
    "proofread_by": "",
    "post_zh_preview": "「好了，快站起来吧」"
  },
  {
    "index": 16,
    "name": "",
    "pre_jp": "倒れた少女の隣にいる気の強そうな少女は、口では言うものの手を出そうとはしない。",
    "post_jp": "倒れた少女の隣にいる気の強そうな少女は、口では言うものの手を出そうとはしない。",
    "pre_zh": "在摔倒的少女身旁，另一位强势的少女嘴上这么说，却没有伸手去扶。",
    "proofread_zh": "",
    "trans_by": "sakura-009",
    "proofread_by": "",
    "post_zh_preview": "在摔倒的少女身旁，另一位强势的少女嘴上这么说，却没有伸手去扶。"
  },
  {
    "index": 17,
    "name": "",
    "pre_jp": "倒れた少女の方は、立ち上がろうとしているものの、どこかを打ったのか痛そうにしていた。",
    "post_jp": "倒れた少女の方は、立ち上がろうとしているものの、どこかを打ったのか痛そうにしていた。",
    "pre_zh": "摔倒的少女试图站起来，但似乎因为撞到了什么地方，表情显得很痛苦。",
    "proofread_zh": "",
    "trans_by": "sakura-009",
    "proofread_by": "",
    "post_zh_preview": "摔倒的少女试图站起来，但似乎因为撞到了什么地方，表情显得很痛苦。"
  },
  {
    "index": 18,
    "name": "有紗",
    "pre_jp": "「…………」",
    "post_jp": "…………",
    "pre_zh": "…………",
    "proofread_zh": "",
    "trans_by": "sakura-009",
    "proofread_by": "",
    "post_zh_preview": "「…………」"
  },
  {
    "index": 19,
    "name": "優花",
    "pre_jp": "「えっ、ちょっと有紗？」",
    "post_jp": "えっ、ちょっと有紗？",
    "pre_zh": "哎，有纱？",
    "proofread_zh": "",
    "trans_by": "sakura-009",
    "proofread_by": "",
    "post_zh_preview": "「哎，有纱？」"
  },
  {
    "index": 20,
    "name": "有紗",
    "pre_jp": "「大丈夫？」",
    "post_jp": "大丈夫？",
    "pre_zh": "你没事吧？",
    "proofread_zh": "",
    "trans_by": "sakura-009",
    "proofread_by": "",
    "post_zh_preview": "「你没事吧？」"
  },
  {
    "index": 21,
    "name": "",
    "pre_jp": "有紗は倒れた少女に駆け寄り、手を差し伸べていた。",
    "post_jp": "有紗は倒れた少女に駆け寄り、手を差し伸べていた。",
    "pre_zh": "有纱跑到摔倒的少女身边，向她伸出了手。",
    "proofread_zh": "",
    "trans_by": "sakura-009",
    "proofread_by": "",
    "post_zh_preview": "有纱跑到摔倒的少女身边，向她伸出了手。"
  },
  {
    "index": 22,
    "name": "",
    "pre_jp": "気弱そうな少女は、差し出された手に一瞬怯えたものの、そっと手を握る。",
    "post_jp": "気弱そうな少女は、差し出された手に一瞬怯えたものの、そっと手を握る。",
    "pre_zh": "怯弱的少女看到伸向自己的手，一瞬间有些害怕，但还是轻轻地握住了。",
    "proofread_zh": "",
    "trans_by": "sakura-009",
    "proofread_by": "",
    "post_zh_preview": "怯弱的少女看到伸向自己的手，一瞬间有些害怕，但还是轻轻地握住了。"
  },
  {
    "index": 23,
    "name": "？？？",
    "pre_jp": "「あ、ありが……んくっ！」",
    "post_jp": "あ、ありが……んくっ！",
    "pre_zh": "谢、谢谢……唔！",
    "proofread_zh": "",
    "trans_by": "sakura-009",
    "proofread_by": "",
    "post_zh_preview": "「谢、谢谢……唔！」"
  },
  {
    "index": 24,
    "name": "",
    "pre_jp": "有紗の手を支えにして立ち上がると、痛そうに顔を歪めてわずかに膝を折った。",
    "post_jp": "有紗の手を支えにして立ち上がると、痛そうに顔を歪めてわずかに膝を折った。",
    "pre_zh": "少女扶着有纱的手站了起来，但表情痛苦地扭曲着，膝盖也微微弯曲。",
    "proofread_zh": "",
    "trans_by": "sakura-009",
    "proofread_by": "",
    "post_zh_preview": "少女扶着有纱的手站了起来，但表情痛苦地扭曲着，膝盖也微微弯曲。"
  },
  {
    "index": 25,
    "name": "有紗",
    "pre_jp": "「ちょっと見せて。……膝、すりむいてるわね」",
    "post_jp": "ちょっと見せて。……膝、すりむいてるわね",
    "pre_zh": "让我看看……膝盖擦破皮了",
    "proofread_zh": "",
    "trans_by": "sakura-009",
    "proofread_by": "",
    "post_zh_preview": "「让我看看……膝盖擦破皮了」"
  },
  {
    "index": 26,
    "name": "",
    "pre_jp": "有紗は手早く濡れティッシュで傷口を拭くと絆創膏を貼り付けた。",
    "post_jp": "有紗は手早く濡れティッシュで傷口を拭くと絆創膏を貼り付けた。",
    "pre_zh": "有纱迅速用湿纸巾擦了擦伤口，然后贴上了创可贴。",
    "proofread_zh": "",
    "trans_by": "sakura-009",
    "proofread_by": "",
    "post_zh_preview": "有纱迅速用湿纸巾擦了擦伤口，然后贴上了创可贴。"
  },
  {
    "index": 27,
    "name": "？？？",
    "pre_jp": "「ありがとう……」",
    "post_jp": "ありがとう……",
    "pre_zh": "谢谢……",
    "proofread_zh": "",
    "trans_by": "sakura-009",
    "proofread_by": "",
    "post_zh_preview": "「谢谢……」"
  },
  {
    "index": 28,
    "name": "有紗",
    "pre_jp": "「どういたしまして」",
    "post_jp": "どういたしまして",
    "pre_zh": "不客气",
    "proofread_zh": "",
    "trans_by": "sakura-009",
    "proofread_by": "",
    "post_zh_preview": "「不客气」"
  },
  {
    "index": 29,
    "name": "？？？",
    "pre_jp": "「何よアンタ。勝手なことしないでよ」",
    "post_jp": "何よアンタ。勝手なことしないでよ",
    "pre_zh": "你干什么啊，别多管闲事好不好",
    "proofread_zh": "",
    "trans_by": "sakura-009",
    "proofread_by": "",
    "post_zh_preview": "「你干什么啊，别多管闲事好不好」"
  },
  {
    "index": 30,
    "name": "有紗",
    "pre_jp": "「転んだから手伝ってあげただけじゃない。何か悪いことでもした？」",
    "post_jp": "転んだから手伝ってあげただけじゃない。何か悪いことでもした？",
    "pre_zh": "你摔倒了，我只是帮你一下而已。我做错什么了吗？",
    "proofread_zh": "",
    "trans_by": "sakura-009",
    "proofread_by": "",
    "post_zh_preview": "「你摔倒了，我只是帮你一下而已。我做错什么了吗？」"
  },
  {
    "index": 31,
    "name": "？？？",
    "pre_jp": "「余計なお世話よ。ほっといて」",
    "post_jp": "余計なお世話よ。ほっといて",
    "pre_zh": "多管闲事。别管我了",
    "proofread_zh": "",
    "trans_by": "sakura-009",
    "proofread_by": "",
    "post_zh_preview": "「多管闲事。别管我了」"
  },
  {
    "index": 32,
    "name": "",
    "pre_jp": "強気な少女はふんと鼻を鳴らすと、不服そうに肩をいからせながらさっさと行ってしまった。",
    "post_jp": "強気な少女はふんと鼻を鳴らすと、不服そうに肩をいからせながらさっさと行ってしまった。",
    "pre_zh": "强势的少女哼了一声，不服气地耸着肩膀快步离开了。",
    "proofread_zh": "",
    "trans_by": "sakura-009",
    "proofread_by": "",
    "post_zh_preview": "强势的少女哼了一声，不服气地耸着肩膀快步离开了。"
  },
  {
    "index": 33,
    "name": "？？？",
    "pre_jp": "「あ、あの、ごめんなさい……」",
    "post_jp": "あ、あの、ごめんなさい……",
    "pre_zh": "那、那个，对不起……",
    "proofread_zh": "",
    "trans_by": "sakura-009",
    "proofread_by": "",
    "post_zh_preview": "「那、那个，对不起……」"
  },
  {
    "index": 34,
    "name": "有紗",
    "pre_jp": "「あなたが謝ることじゃないわ。気にしないで」",
    "post_jp": "あなたが謝ることじゃないわ。気にしないで",
    "pre_zh": "你不用道歉的，别在意",
    "proofread_zh": "",
    "trans_by": "sakura-009",
    "proofread_by": "",
    "post_zh_preview": "「你不用道歉的，别在意」"
  },
  {
    "index": 35,
    "name": "？？？",
    "pre_jp": "「何やってるの。行くわよ！」",
    "post_jp": "何やってるの。行くわよ！",
    "pre_zh": "你在干什么呢，快走啊！",
    "proofread_zh": "",
    "trans_by": "sakura-009",
    "proofread_by": "",
    "post_zh_preview": "「你在干什么呢，快走啊！」"
  },
  {
    "index": 36,
    "name": "？？？",
    "pre_jp": "「あ、うん……」",
    "post_jp": "あ、うん……",
    "pre_zh": "啊，嗯……",
    "proofread_zh": "",
    "trans_by": "sakura-009",
    "proofread_by": "",
    "post_zh_preview": "「啊，嗯……」"
  },
  {
    "index": 37,
    "name": "",
    "pre_jp": "一瞬怯えるように震えた後、大人しそうな少女は有紗に深く頭を下げて走り去っていった。",
    "post_jp": "一瞬怯えるように震えた後、大人しそうな少女は有紗に深く頭を下げて走り去っていった。",
    "pre_zh": "怯生生的少女颤抖了一下，然后向有纱深深鞠了一躬，转身跑开了。",
    "proofread_zh": "",
    "trans_by": "sakura-009",
    "proofread_by": "",
    "post_zh_preview": "怯生生的少女颤抖了一下，然后向有纱深深鞠了一躬，转身跑开了。"
  },
  {
    "index": 38,
    "name": "優花",
    "pre_jp": "「なんなのあいつ。態度悪いわね……」",
    "post_jp": "なんなのあいつ。態度悪いわね……",
    "pre_zh": "那家伙怎么回事，态度真差……",
    "proofread_zh": "",
    "trans_by": "sakura-009",
    "proofread_by": "",
    "post_zh_preview": "「那家伙怎么回事，态度真差……」"
  },
  {
    "index": 39,
    "name": "美鈴",
    "pre_jp": "「うん……あの子、大丈夫かな」",
    "post_jp": "うん……あの子、大丈夫かな",
    "pre_zh": "嗯……那女孩没事吧",
    "proofread_zh": "",
    "trans_by": "sakura-009",
    "proofread_by": "",
    "post_zh_preview": "「嗯……那女孩没事吧」"
  },
  {
    "index": 40,
    "name": "有紗",
    "pre_jp": "「怪我の方は大丈夫だと思うけど……あんまりいい雰囲気じゃなかったわね」",
    "post_jp": "怪我の方は大丈夫だと思うけど……あんまりいい雰囲気じゃなかったわね",
    "pre_zh": "受伤应该没什么大碍……但气氛好像有点尴尬",
    "proofread_zh": "",
    "trans_by": "sakura-009",
    "proofread_by": "",
    "post_zh_preview": "「受伤应该没什么大碍……但气氛好像有点尴尬」"
  },
  {
    "index": 41,
    "name": "美鈴",
    "pre_jp": "「でも、有紗ちゃん。ちょっと変わったね」",
    "post_jp": "でも、有紗ちゃん。ちょっと変わったね",
    "pre_zh": "不过，有纱，你好像变了呢",
    "proofread_zh": "",
    "trans_by": "sakura-009",
    "proofread_by": "",
    "post_zh_preview": "「不过，有纱，你好像变了呢」"
  },
  {
    "index": 42,
    "name": "優花",
    "pre_jp": "「うんうん。昔なら興味なしって通り過ぎてたと思うよ？」",
    "post_jp": "うんうん。昔なら興味なしって通り過ぎてたと思うよ？",
    "pre_zh": "嗯嗯。如果是以前的你，应该会直接走掉吧",
    "proofread_zh": "",
    "trans_by": "sakura-009",
    "proofread_by": "",
    "post_zh_preview": "「嗯嗯。如果是以前的你，应该会直接走掉吧」"
  },
  {
    "index": 43,
    "name": "有紗",
    "pre_jp": "「そうかな……そうかも」",
    "post_jp": "そうかな……そうかも",
    "pre_zh": "是吗……可能吧",
    "proofread_zh": "",
    "trans_by": "sakura-009",
    "proofread_by": "",
    "post_zh_preview": "「是吗……可能吧」"
  },
  {
    "index": 44,
    "name": "",
    "pre_jp": "有紗自身、自分の心境の変化に驚いていた。",
    "post_jp": "有紗自身、自分の心境の変化に驚いていた。",
    "pre_zh": "有纱也对自己的心境变化感到惊讶。",
    "proofread_zh": "",
    "trans_by": "sakura-009",
    "proofread_by": "",
    "post_zh_preview": "有纱也对自己的心境变化感到惊讶。"
  },
  {
    "index": 45,
    "name": "",
    "pre_jp": "さっきの光景を見た瞬間、自然と身体が動いていた。",
    "post_jp": "さっきの光景を見た瞬間、自然と身体が動いていた。",
    "pre_zh": "看到刚才那一幕的瞬间，身体就自然地动了起来。",
    "proofread_zh": "",
    "trans_by": "sakura-009",
    "proofread_by": "",
    "post_zh_preview": "看到刚才那一幕的瞬间，身体就自然地动了起来。"
  },
  {
    "index": 46,
    "name": "",
    "pre_jp": "打算や意識しての行動ではなかったことが、有紗の中の何かが変わりつつあることを明確に示していた。",
    "post_jp": "打算や意識しての行動ではなかったことが、有紗の中の何かが変わりつつあることを明確に示していた。",
    "pre_zh": "这说明有纱的心境确实发生了变化，而且不是出于算计或刻意为之。",
    "proofread_zh": "",
    "trans_by": "sakura-009",
    "proofread_by": "",
    "post_zh_preview": "这说明有纱的心境确实发生了变化，而且不是出于算计或刻意为之。"
  },
  {
    "index": 47,
    "name": "優花",
    "pre_jp": "「それにしても、有紗って何でも持ってるんだね。絆創膏はまだしも、濡れティッシュなんて普通持ってないよ？」",
    "post_jp": "それにしても、有紗って何でも持ってるんだね。絆創膏はまだしも、濡れティッシュなんて普通持ってないよ？",
    "pre_zh": "话说回来，你真是什么都有啊。创可贴就算了，湿纸巾一般可不会随身携带吧？",
    "proofread_zh": "",
    "trans_by": "sakura-009",
    "proofread_by": "",
    "post_zh_preview": "「话说回来，你真是什么都有啊。创可贴就算了，湿纸巾一般可不会随身携带吧？」"
  },
  {
    "index": 48,
    "name": "有紗",
    "pre_jp": "「何かの時に使うからって買って、そのまま入れっぱなしになってただけだけどね」",
    "post_jp": "何かの時に使うからって買って、そのまま入れっぱなしになってただけだけどね",
    "pre_zh": "我买了备用的，然后就一直放在包里",
    "proofread_zh": "",
    "trans_by": "sakura-009",
    "proofread_by": "",
    "post_zh_preview": "「我买了备用的，然后就一直放在包里」"
  },
  {
    "index": 49,
    "name": "優花",
    "pre_jp": "「ふぅん……。準備いいね」",
    "post_jp": "ふぅん……。準備いいね",
    "pre_zh": "是吗……准备得真周到啊",
    "proofread_zh": "",
    "trans_by": "sakura-009",
    "proofread_by": "",
    "post_zh_preview": "「是吗……准备得真周到啊」"
  },
  {
    "index": 50,
    "name": "有紗",
    "pre_jp": "「偶然だって。もうっ……」",
    "post_jp": "偶然だって。もうっ……",
    "pre_zh": "只是碰巧而已啦……",
    "proofread_zh": "",
    "trans_by": "sakura-009",
    "proofread_by": "",
    "post_zh_preview": "「只是碰巧而已啦……」"
  },
  {
    "index": 51,
    "name": "",
    "pre_jp": "ちょっと褒められただけで顔が赤くなってしまう。",
    "post_jp": "ちょっと褒められただけで顔が赤くなってしまう。",
    "pre_zh": "只是被夸了一句，就羞得满脸通红。",
    "proofread_zh": "",
    "trans_by": "sakura-009",
    "proofread_by": "",
    "post_zh_preview": "只是被夸了一句，就羞得满脸通红。"
  },
  {
    "index": 52,
    "name": "",
    "pre_jp": "そんな子供みたいな自分が、また恥ずかしかった。",
    "post_jp": "そんな子供みたいな自分が、また恥ずかしかった。",
    "pre_zh": "这么幼稚的自己，让有纱感到很羞耻。",
    "proofread_zh": "",
    "trans_by": "sakura-009",
    "proofread_by": "",
    "post_zh_preview": "这么幼稚的自己，让有纱感到很羞耻。"
  }
]