[
  {
    "index": 1,
    "name": "有紗",
    "pre_jp": "「それで、何の参考書を探すつもりだったの？」",
    "post_jp": "それで、何の参考書を探すつもりだったの？",
    "pre_zh": "所以，你到底想找什么参考书？",
    "proofread_zh": "",
    "trans_by": "sakura-009",
    "proofread_by": "",
    "post_zh_preview": "「所以，你到底想找什么参考书？」"
  },
  {
    "index": 2,
    "name": "ユーリ",
    "pre_jp": "「えっと……」",
    "post_jp": "えっと……",
    "pre_zh": "呃……",
    "proofread_zh": "",
    "trans_by": "sakura-009",
    "proofread_by": "",
    "post_zh_preview": "「呃……」"
  },
  {
    "index": 3,
    "name": "",
    "pre_jp": "ユーリは有紗の問いに口ごもったままうつむいてしまう。",
    "post_jp": "尤莉は有紗の問いに口ごもったままうつむいてしまう。",
    "pre_zh": "尤莉被有纱这么一问，顿时低下了头，支支吾吾的。",
    "proofread_zh": "",
    "trans_by": "sakura-009",
    "proofread_by": "",
    "post_zh_preview": "尤莉被有纱这么一问，顿时低下了头，支支吾吾的。"
  },
  {
    "index": 4,
    "name": "",
    "pre_jp": "何か気まずそうなところを見ると、もしかしたら参考書というのは言い訳なのではないかと思えてきてしまう。",
    "post_jp": "何か気まずそうなところを見ると、もしかしたら参考書というのは言い訳なのではないかと思えてきてしまう。",
    "pre_zh": "看她这副尴尬的样子，有纱开始怀疑她是不是在撒谎。",
    "proofread_zh": "",
    "trans_by": "sakura-009",
    "proofread_by": "",
    "post_zh_preview": "看她这副尴尬的样子，有纱开始怀疑她是不是在撒谎。"
  },
  {
    "index": 5,
    "name": "有紗",
    "pre_jp": "（でも、それだったら何か他に一緒についてきて欲しい理由があったってことになるし……）",
    "post_jp": "（でも、それだったら何か他に一緒についてきて欲しい理由があったってことになるし……）",
    "pre_zh": "（不过，如果她真的在撒谎，那她应该会编一个更合理的理由才对……）",
    "proofread_zh": "",
    "trans_by": "sakura-009",
    "proofread_by": "",
    "post_zh_preview": "（不过，如果她真的在撒谎，那她应该会编一个更合理的理由才对……）"
  },
  {
    "index": 6,
    "name": "",
    "pre_jp": "考えてみても、他の理由が思いつかない。",
    "post_jp": "考えてみても、他の理由が思いつかない。",
    "pre_zh": "有纱想来想去，也想不出其他理由。",
    "proofread_zh": "",
    "trans_by": "sakura-009",
    "proofread_by": "",
    "post_zh_preview": "有纱想来想去，也想不出其他理由。"
  },
  {
    "index": 7,
    "name": "",
    "pre_jp": "とりあえず、本屋に行って聞いてみれば分かる話だ。",
    "post_jp": "とりあえず、本屋に行って聞いてみれば分かる話だ。",
    "pre_zh": "反正去了书店就知道了。",
    "proofread_zh": "",
    "trans_by": "sakura-009",
    "proofread_by": "",
    "post_zh_preview": "反正去了书店就知道了。"
  },
  {
    "index": 8,
    "name": "",
    "pre_jp": "有紗は深く考えるのをやめ、本屋への道を進んでいく。",
    "post_jp": "有紗は深く考えるのをやめ、本屋への道を進んでいく。",
    "pre_zh": "于是有纱不再多想，朝着书店的方向走去。",
    "proofread_zh": "",
    "trans_by": "sakura-009",
    "proofread_by": "",
    "post_zh_preview": "于是有纱不再多想，朝着书店的方向走去。"
  },
  {
    "index": 9,
    "name": "ユーリ",
    "pre_jp": "「ありさ、やっぱり参考書を買いに行くのはまた今度に……」",
    "post_jp": "ありさ、やっぱり参考書を買いに行くのはまた今度に……",
    "pre_zh": "亚里沙，我们还是下次再来买参考书吧……",
    "proofread_zh": "",
    "trans_by": "sakura-009",
    "proofread_by": "",
    "post_zh_preview": "「亚里沙，我们还是下次再来买参考书吧……」"
  },
  {
    "index": 10,
    "name": "有紗",
    "pre_jp": "「きゃっ！？　な、何？」",
    "post_jp": "きゃっ！？　な、何？",
    "pre_zh": "呀！？怎、怎么回事？",
    "proofread_zh": "",
    "trans_by": "sakura-009",
    "proofread_by": "",
    "post_zh_preview": "「呀！？怎、怎么回事？」"
  },
  {
    "index": 11,
    "name": "",
    "pre_jp": "突然、目の前で轟音が響いたかと思うと、有紗の胸を締めつける痛みが走った。",
    "post_jp": "突然、目の前で轟音が響いたかと思うと、有紗の胸を締めつける痛みが走った。",
    "pre_zh": "突然，有纱的眼前传来一声巨响，紧接着胸口传来一阵剧痛。",
    "proofread_zh": "",
    "trans_by": "sakura-009",
    "proofread_by": "",
    "post_zh_preview": "突然，有纱的眼前传来一声巨响，紧接着胸口传来一阵剧痛。"
  },
  {
    "index": 12,
    "name": "ザクール",
    "pre_jp": "「ギビッ、ギヒヒッ！」",
    "post_jp": "ギビッ、ギヒヒッ！",
    "pre_zh": "叽叽、嘻嘻嘻！",
    "proofread_zh": "",
    "trans_by": "sakura-009",
    "proofread_by": "",
    "post_zh_preview": "「叽叽、嘻嘻嘻！」"
  },
  {
    "index": 13,
    "name": "有紗",
    "pre_jp": "（あれは……この前ショッピングモールに現れた召喚獣！？）",
    "post_jp": "（あれは……この前ショッピングモールに現れた召喚獣！？）",
    "pre_zh": "（那是……之前在购物中心出现的召唤兽！？）",
    "proofread_zh": "",
    "trans_by": "sakura-009",
    "proofread_by": "",
    "post_zh_preview": "（那是……之前在购物中心出现的召唤兽！？）"
  },
  {
    "index": 14,
    "name": "",
    "pre_jp": "蕾のように閉じた口から涎を垂らし、肩を揺らして笑う姿に、有紗は背筋が寒くなるのを感じた。",
    "post_jp": "蕾のように閉じた口から涎を垂らし、肩を揺らして笑う姿に、有紗は背筋が寒くなるのを感じた。",
    "pre_zh": "它那紧闭的花蕾般的嘴巴流着口水，肩膀抖动着发出笑声的样子，让有纱感到一阵恶寒。",
    "proofread_zh": "",
    "trans_by": "sakura-009",
    "proofread_by": "",
    "post_zh_preview": "它那紧闭的花蕾般的嘴巴流着口水，肩膀抖动着发出笑声的样子，让有纱感到一阵恶寒。"
  },
  {
    "index": 15,
    "name": "",
    "pre_jp": "すぐさま人目のつかないところに走ろうとすると、その手が急に掴まれる。",
    "post_jp": "すぐさま人目のつかないところに走ろうとすると、その手が急に掴まれる。",
    "pre_zh": "正当她准备跑向没有人烟的地方时，突然被抓住了手。",
    "proofread_zh": "",
    "trans_by": "sakura-009",
    "proofread_by": "",
    "post_zh_preview": "正当她准备跑向没有人烟的地方时，突然被抓住了手。"
  },
  {
    "index": 16,
    "name": "ユーリ",
    "pre_jp": "「あ、ありさ……」",
    "post_jp": "あ、ありさ……",
    "pre_zh": "亚、亚里沙……",
    "proofread_zh": "",
    "trans_by": "sakura-009",
    "proofread_by": "",
    "post_zh_preview": "「亚、亚里沙……」"
  },
  {
    "index": 17,
    "name": "有紗",
    "pre_jp": "「っ！？　ユーリ、一緒に逃げよう。ここにいたら危ないわ」",
    "post_jp": "っ！？　尤莉、一緒に逃げよう。ここにいたら危ないわ",
    "pre_zh": "啊！？尤莉，我们快逃吧。留在这里太危险了",
    "proofread_zh": "",
    "trans_by": "sakura-009",
    "proofread_by": "",
    "post_zh_preview": "「啊！？尤莉，我们快逃吧。留在这里太危险了」"
  },
  {
    "index": 18,
    "name": "ユーリ",
    "pre_jp": "「う、うん……」",
    "post_jp": "う、うん……",
    "pre_zh": "嗯、嗯……",
    "proofread_zh": "",
    "trans_by": "sakura-009",
    "proofread_by": "",
    "post_zh_preview": "「嗯、嗯……」"
  },
  {
    "index": 19,
    "name": "",
    "pre_jp": "このままユーリをこの場に置いて行くわけにはいかない。",
    "post_jp": "このまま尤莉をこの場に置いて行くわけにはいかない。",
    "pre_zh": "有纱不能把尤莉留在这里。",
    "proofread_zh": "",
    "trans_by": "sakura-009",
    "proofread_by": "",
    "post_zh_preview": "有纱不能把尤莉留在这里。"
  },
  {
    "index": 20,
    "name": "",
    "pre_jp": "とはいえ、ユーリに正体を晒すわけにもいかない。",
    "post_jp": "とはいえ、尤莉に正体を晒すわけにもいかない。",
    "pre_zh": "但是她又不能暴露自己的身份。",
    "proofread_zh": "",
    "trans_by": "sakura-009",
    "proofread_by": "",
    "post_zh_preview": "但是她又不能暴露自己的身份。"
  },
  {
    "index": 21,
    "name": "",
    "pre_jp": "有紗は焦りを覚えながら走り出す。",
    "post_jp": "有紗は焦りを覚えながら走り出す。",
    "pre_zh": "有纱焦急地跑了起来。",
    "proofread_zh": "",
    "trans_by": "sakura-009",
    "proofread_by": "",
    "post_zh_preview": "有纱焦急地跑了起来。"
  },
  {
    "index": 22,
    "name": "セラ",
    "pre_jp": "「おっと、どこに行くつもり？」",
    "post_jp": "おっと、どこに行くつもり？",
    "pre_zh": "哎呀，你想去哪里？",
    "proofread_zh": "",
    "trans_by": "sakura-009",
    "proofread_by": "",
    "post_zh_preview": "「哎呀，你想去哪里？」"
  },
  {
    "index": 23,
    "name": "有紗",
    "pre_jp": "「くっ！？」",
    "post_jp": "くっ！？",
    "pre_zh": "唔！？",
    "proofread_zh": "",
    "trans_by": "sakura-009",
    "proofread_by": "",
    "post_zh_preview": "「唔！？」"
  },
  {
    "index": 24,
    "name": "",
    "pre_jp": "目の前で地面が叩かれ、思わず足を止めてしまう。",
    "post_jp": "目の前で地面が叩かれ、思わず足を止めてしまう。",
    "pre_zh": "面前的地面突然被拍了一下，有纱不由得停下了脚步。",
    "proofread_zh": "",
    "trans_by": "sakura-009",
    "proofread_by": "",
    "post_zh_preview": "面前的地面突然被拍了一下，有纱不由得停下了脚步。"
  },
  {
    "index": 25,
    "name": "",
    "pre_jp": "振り向くと、ザクールとセラが有紗達に視線を向けていた。",
    "post_jp": "振り向くと、ザクールと莎拉が有紗達に視線を向けていた。",
    "pre_zh": "有纱回头一看，发现札库罗和莎拉正盯着自己。",
    "proofread_zh": "",
    "trans_by": "sakura-009",
    "proofread_by": "",
    "post_zh_preview": "有纱回头一看，发现札库罗和莎拉正盯着自己。"
  },
  {
    "index": 26,
    "name": "",
    "pre_jp": "まるで、有紗の正体を知っているかのように。",
    "post_jp": "まるで、有紗の正体を知っているかのように。",
    "pre_zh": "仿佛早就知道有纱的身份一样。",
    "proofread_zh": "",
    "trans_by": "sakura-009",
    "proofread_by": "",
    "post_zh_preview": "仿佛早就知道有纱的身份一样。"
  },
  {
    "index": 27,
    "name": "セラ",
    "pre_jp": "「今日の獲物はアンタ達よ。ザクール、行きなさい！」",
    "post_jp": "今日の獲物はアンタ達よ。ザクール、行きなさい！",
    "pre_zh": "今天的目标就是你们。札库罗，上吧！",
    "proofread_zh": "",
    "trans_by": "sakura-009",
    "proofread_by": "",
    "post_zh_preview": "「今天的目标就是你们。札库罗，上吧！」"
  },
  {
    "index": 28,
    "name": "ザクール",
    "pre_jp": "「グビッ、ギビィ……ッ」",
    "post_jp": "グビッ、ギビィ……ッ",
    "pre_zh": "咕哔，叽哔……",
    "proofread_zh": "",
    "trans_by": "sakura-009",
    "proofread_by": "",
    "post_zh_preview": "「咕哔，叽哔……」"
  },
  {
    "index": 29,
    "name": "",
    "pre_jp": "ザクールが有紗達に向かってゆっくり歩いてくる。",
    "post_jp": "ザクールが有紗達に向かってゆっくり歩いてくる。",
    "pre_zh": "札库罗缓缓地朝有纱她们走了过来。",
    "proofread_zh": "",
    "trans_by": "sakura-009",
    "proofread_by": "",
    "post_zh_preview": "札库罗缓缓地朝有纱她们走了过来。"
  },
  {
    "index": 30,
    "name": "",
    "pre_jp": "周りには自分達の方向に向かってこなかったと安心している人々が、有紗達の様子をつぶさに観察していた。",
    "post_jp": "周りには自分達の方向に向かってこなかったと安心している人々が、有紗達の様子をつぶさに観察していた。",
    "pre_zh": "周围的人们看到它没有朝自己走来，都松了口气，但同时也在仔细观察着有纱她们的举动。",
    "proofread_zh": "",
    "trans_by": "sakura-009",
    "proofread_by": "",
    "post_zh_preview": "周围的人们看到它没有朝自己走来，都松了口气，但同时也在仔细观察着有纱她们的举动。"
  },
  {
    "index": 31,
    "name": "",
    "pre_jp": "有紗達の行動次第では、自分達がターゲットになる可能性もなくはないからだ。",
    "post_jp": "有紗達の行動次第では、自分達がターゲットになる可能性もなくはないからだ。",
    "pre_zh": "毕竟她们的行动可能会让自己成为下一个目标。",
    "proofread_zh": "",
    "trans_by": "sakura-009",
    "proofread_by": "",
    "post_zh_preview": "毕竟她们的行动可能会让自己成为下一个目标。"
  },
  {
    "index": 32,
    "name": "有紗",
    "pre_jp": "（どうしよう、このままじゃ召喚獣に捕まっちゃう。その前に、せめてユーリだけでも逃がさないと……）",
    "post_jp": "（どうしよう、このままじゃ召喚獣に捕まっちゃう。その前に、せめて尤莉だけでも逃がさないと……）",
    "pre_zh": "（怎么办，这样下去会被召唤兽抓住的。至少要让尤莉逃走……）",
    "proofread_zh": "",
    "trans_by": "sakura-009",
    "proofread_by": "",
    "post_zh_preview": "（怎么办，这样下去会被召唤兽抓住的。至少要让尤莉逃走……）"
  },
  {
    "index": 33,
    "name": "",
    "pre_jp": "ユーリの手は有紗をしっかりと握ったままで離す様子がない。",
    "post_jp": "尤莉の手は有紗をしっかりと握ったままで離す様子がない。",
    "pre_zh": "尤莉的手紧紧地握着有纱，没有要松开的意思。",
    "proofread_zh": "",
    "trans_by": "sakura-009",
    "proofread_by": "",
    "post_zh_preview": "尤莉的手紧紧地握着有纱，没有要松开的意思。"
  },
  {
    "index": 34,
    "name": "",
    "pre_jp": "ここで無理に引きはがすようなことをすれば、ユーリの信用を裏切ってしまう気がして、振り払うことなど出来ない。",
    "post_jp": "ここで無理に引きはがすようなことをすれば、尤莉の信用を裏切ってしまう気がして、振り払うことなど出来ない。",
    "pre_zh": "有纱觉得如果强行拉开尤莉的手，会辜负尤莉对自己的信任，所以无法甩开她的手。",
    "proofread_zh": "",
    "trans_by": "sakura-009",
    "proofread_by": "",
    "post_zh_preview": "有纱觉得如果强行拉开尤莉的手，会辜负尤莉对自己的信任，所以无法甩开她的手。"
  },
  {
    "index": 35,
    "name": "",
    "pre_jp": "となれば、ユーリを連れて逃げる以外に方法はなかった。",
    "post_jp": "となれば、尤莉を連れて逃げる以外に方法はなかった。",
    "pre_zh": "既然如此，那就只能带着她一起逃跑了。",
    "proofread_zh": "",
    "trans_by": "sakura-009",
    "proofread_by": "",
    "post_zh_preview": "既然如此，那就只能带着她一起逃跑了。"
  },
  {
    "index": 36,
    "name": "有紗",
    "pre_jp": "「ユーリ、私が合図したら、頑張って走ってね」",
    "post_jp": "尤莉、私が合図したら、頑張って走ってね",
    "pre_zh": "尤莉，等我一打信号，你就拼命跑",
    "proofread_zh": "",
    "trans_by": "sakura-009",
    "proofread_by": "",
    "post_zh_preview": "「尤莉，等我一打信号，你就拼命跑」"
  },
  {
    "index": 37,
    "name": "ユーリ",
    "pre_jp": "「えっ、う、うん……」",
    "post_jp": "えっ、う、うん……",
    "pre_zh": "哎，嗯、嗯……",
    "proofread_zh": "",
    "trans_by": "sakura-009",
    "proofread_by": "",
    "post_zh_preview": "「哎，嗯、嗯……」"
  },
  {
    "index": 38,
    "name": "有紗",
    "pre_jp": "「くぅっ！」",
    "post_jp": "くぅっ！",
    "pre_zh": "唔！",
    "proofread_zh": "",
    "trans_by": "sakura-009",
    "proofread_by": "",
    "post_zh_preview": "「唔！」"
  },
  {
    "index": 39,
    "name": "",
    "pre_jp": "有紗が走る素振りを見せると、ザクールは触手を振りかざして行く手を遮る。",
    "post_jp": "有紗が走る素振りを見せると、ザクールは触手を振りかざして行く手を遮る。",
    "pre_zh": "有纱刚一做出逃跑的准备，札库罗就挥舞着触手挡住了去路。",
    "proofread_zh": "",
    "trans_by": "sakura-009",
    "proofread_by": "",
    "post_zh_preview": "有纱刚一做出逃跑的准备，札库罗就挥舞着触手挡住了去路。"
  },
  {
    "index": 40,
    "name": "",
    "pre_jp": "普通に逃げだそうにも、これでは触手の餌食になるだけだ。",
    "post_jp": "普通に逃げだそうにも、これでは触手の餌食になるだけだ。",
    "pre_zh": "就算想逃跑，也只会成为触手的饵食。",
    "proofread_zh": "",
    "trans_by": "sakura-009",
    "proofread_by": "",
    "post_zh_preview": "就算想逃跑，也只会成为触手的饵食。"
  },
  {
    "index": 41,
    "name": "",
    "pre_jp": "可能性があるとすれば、ザクールが有紗達から目を離す隙を見つけるしかない。",
    "post_jp": "可能性があるとすれば、ザクールが有紗達から目を離す隙を見つけるしかない。",
    "pre_zh": "要想逃走，就只能趁札库罗不注意的时候。",
    "proofread_zh": "",
    "trans_by": "sakura-009",
    "proofread_by": "",
    "post_zh_preview": "要想逃走，就只能趁札库罗不注意的时候。"
  },
  {
    "index": 42,
    "name": "有紗",
    "pre_jp": "（でも、そんな瞬間……本当にあるの？）",
    "post_jp": "（でも、そんな瞬間……本当にあるの？）",
    "pre_zh": "（但是，真的会有那样的瞬间吗？）",
    "proofread_zh": "",
    "trans_by": "sakura-009",
    "proofread_by": "",
    "post_zh_preview": "（但是，真的会有那样的瞬间吗？）"
  },
  {
    "index": 43,
    "name": "",
    "pre_jp": "変身していない状態では、反応速度も人並みだ。",
    "post_jp": "変身していない状態では、反応速度も人並みだ。",
    "pre_zh": "在没有变身的状态下，自己的反应速度跟常人无异。",
    "proofread_zh": "",
    "trans_by": "sakura-009",
    "proofread_by": "",
    "post_zh_preview": "在没有变身的状态下，自己的反应速度跟常人无异。"
  },
  {
    "index": 44,
    "name": "",
    "pre_jp": "もし、ザクールの隙を見つけたとしても反応出来るかどうか。",
    "post_jp": "もし、ザクールの隙を見つけたとしても反応出来るかどうか。",
    "pre_zh": "就算真的发现了札库罗的破绽，自己也不一定能反应过来。",
    "proofread_zh": "",
    "trans_by": "sakura-009",
    "proofread_by": "",
    "post_zh_preview": "就算真的发现了札库罗的破绽，自己也不一定能反应过来。"
  },
  {
    "index": 45,
    "name": "",
    "pre_jp": "その上、その間に逃げおおせるかどうかも怪しい。",
    "post_jp": "その上、その間に逃げおおせるかどうかも怪しい。",
    "pre_zh": "而且，能不能在那短短的一瞬间逃走都是个问题。",
    "proofread_zh": "",
    "trans_by": "sakura-009",
    "proofread_by": "",
    "post_zh_preview": "而且，能不能在那短短的一瞬间逃走都是个问题。"
  },
  {
    "index": 46,
    "name": "有紗",
    "pre_jp": "（最悪の場合は、ばれるのを覚悟で変身するしかない）",
    "post_jp": "（最悪の場合は、ばれるのを覚悟で変身するしかない）",
    "pre_zh": "（最坏的情况下，只能做好暴露身份的心理准备变身了）",
    "proofread_zh": "",
    "trans_by": "sakura-009",
    "proofread_by": "",
    "post_zh_preview": "（最坏的情况下，只能做好暴露身份的心理准备变身了）"
  },
  {
    "index": 47,
    "name": "",
    "pre_jp": "有紗はフリーになっている左手をぐっと握りしめる。",
    "post_jp": "有紗はフリーになっている左手をぐっと握りしめる。",
    "pre_zh": "有纱紧紧地握住了空出来的左手。",
    "proofread_zh": "",
    "trans_by": "sakura-009",
    "proofread_by": "",
    "post_zh_preview": "有纱紧紧地握住了空出来的左手。"
  },
  {
    "index": 48,
    "name": "",
    "pre_jp": "マグナスが気づいて来てくれるとしても、さすがにここに来るまでには時間がかかる。",
    "post_jp": "玛格纳斯が気づいて来てくれるとしても、さすがにここに来るまでには時間がかかる。",
    "pre_zh": "就算玛格纳斯察觉到了这边的情况，也得花上不少时间才能赶到这里。",
    "proofread_zh": "",
    "trans_by": "sakura-009",
    "proofread_by": "",
    "post_zh_preview": "就算玛格纳斯察觉到了这边的情况，也得花上不少时间才能赶到这里。"
  },
  {
    "index": 49,
    "name": "",
    "pre_jp": "正確な位置が分かるかどうかということが、これほど意味を持つとは思わなかった。",
    "post_jp": "正確な位置が分かるかどうかということが、これほど意味を持つとは思わなかった。",
    "pre_zh": "有纱没想到，是否能知道正确的位置，竟然会带来这么大的意义。",
    "proofread_zh": "",
    "trans_by": "sakura-009",
    "proofread_by": "",
    "post_zh_preview": "有纱没想到，是否能知道正确的位置，竟然会带来这么大的意义。"
  },
  {
    "index": 50,
    "name": "ザクール",
    "pre_jp": "「グ……ギビッ、ギヒッ？」",
    "post_jp": "グ……ギビッ、ギヒッ？",
    "pre_zh": "咕……叽、叽嘻？",
    "proofread_zh": "",
    "trans_by": "sakura-009",
    "proofread_by": "",
    "post_zh_preview": "「咕……叽、叽嘻？」"
  },
  {
    "index": 51,
    "name": "",
    "pre_jp": "ザクールは首をかしげ、また触手を振り下ろした。",
    "post_jp": "ザクールは首をかしげ、また触手を振り下ろした。",
    "pre_zh": "札库罗歪了歪脑袋，又挥下了触手。",
    "proofread_zh": "",
    "trans_by": "sakura-009",
    "proofread_by": "",
    "post_zh_preview": "札库罗歪了歪脑袋，又挥下了触手。"
  },
  {
    "index": 52,
    "name": "",
    "pre_jp": "だが、それは有紗が逃げようとしている方向でもなく、まったく見当違いのところを叩いていた。",
    "post_jp": "だが、それは有紗が逃げようとしている方向でもなく、まったく見当違いのところを叩いていた。",
    "pre_zh": "但是，触手并没有击中有纱，而是打在了完全不同的地方。",
    "proofread_zh": "",
    "trans_by": "sakura-009",
    "proofread_by": "",
    "post_zh_preview": "但是，触手并没有击中有纱，而是打在了完全不同的地方。"
  },
  {
    "index": 53,
    "name": "セラ",
    "pre_jp": "「ん？　ザクール、アンタ何やってんのよ」",
    "post_jp": "ん？　ザクール、アンタ何やってんのよ",
    "pre_zh": "嗯？札库罗，你在干什么呢",
    "proofread_zh": "",
    "trans_by": "sakura-009",
    "proofread_by": "",
    "post_zh_preview": "「嗯？札库罗，你在干什么呢」"
  },
  {
    "index": 54,
    "name": "有紗",
    "pre_jp": "（召喚獣の反応が強くなってる……？　おかしいわ、そんなに距離が変わってないのに）",
    "post_jp": "（召喚獣の反応が強くなってる……？　おかしいわ、そんなに距離が変わってないのに）",
    "pre_zh": "（召唤兽的反应变强了……？好奇怪啊，明明距离没有变化）",
    "proofread_zh": "",
    "trans_by": "sakura-009",
    "proofread_by": "",
    "post_zh_preview": "（召唤兽的反应变强了……？好奇怪啊，明明距离没有变化）"
  },
  {
    "index": 55,
    "name": "",
    "pre_jp": "胸をかき乱す感覚は、さっきより強くなってきている。",
    "post_jp": "胸をかき乱す感覚は、さっきより強くなってきている。",
    "pre_zh": "胸口的骚动感比刚才更加强烈了。",
    "proofread_zh": "",
    "trans_by": "sakura-009",
    "proofread_by": "",
    "post_zh_preview": "胸口的骚动感比刚才更加强烈了。"
  },
  {
    "index": 56,
    "name": "",
    "pre_jp": "それほど距離が変わっていないのに、ここまで強くなるのは明らかにおかしい。",
    "post_jp": "それほど距離が変わっていないのに、ここまで強くなるのは明らかにおかしい。",
    "pre_zh": "明明距离没有变化，反应却变得这么强烈，这明显很奇怪。",
    "proofread_zh": "",
    "trans_by": "sakura-009",
    "proofread_by": "",
    "post_zh_preview": "明明距离没有变化，反应却变得这么强烈，这明显很奇怪。"
  },
  {
    "index": 57,
    "name": "",
    "pre_jp": "少なくとも、今まではなかった感覚に、有紗は焦りを覚えずにはいられない。",
    "post_jp": "少なくとも、今まではなかった感覚に、有紗は焦りを覚えずにはいられない。",
    "pre_zh": "至少，有纱从未有过这种感觉，这让她不由得感到焦躁不安。",
    "proofread_zh": "",
    "trans_by": "sakura-009",
    "proofread_by": "",
    "post_zh_preview": "至少，有纱从未有过这种感觉，这让她不由得感到焦躁不安。"
  },
  {
    "index": 58,
    "name": "ユーリ",
    "pre_jp": "「こんな……何か、おかしい」",
    "post_jp": "こんな……何か、おかしい",
    "pre_zh": "这……感觉，有点奇怪",
    "proofread_zh": "",
    "trans_by": "sakura-009",
    "proofread_by": "",
    "post_zh_preview": "「这……感觉，有点奇怪」"
  },
  {
    "index": 59,
    "name": "有紗",
    "pre_jp": "「ユーリ、大丈夫？」",
    "post_jp": "尤莉、大丈夫？",
    "pre_zh": "尤莉，你没事吧？",
    "proofread_zh": "",
    "trans_by": "sakura-009",
    "proofread_by": "",
    "post_zh_preview": "「尤莉，你没事吧？」"
  },
  {
    "index": 60,
    "name": "",
    "pre_jp": "ユーリは額に汗を滲ませ、目の前の召喚獣とセラを見ながら顔をしかめる。",
    "post_jp": "尤莉は額に汗を滲ませ、目の前の召喚獣と莎拉を見ながら顔をしかめる。",
    "pre_zh": "尤莉的额头渗出了汗水，她皱着眉头看着眼前的召唤兽和莎拉。",
    "proofread_zh": "",
    "trans_by": "sakura-009",
    "proofread_by": "",
    "post_zh_preview": "尤莉的额头渗出了汗水，她皱着眉头看着眼前的召唤兽和莎拉。"
  },
  {
    "index": 61,
    "name": "",
    "pre_jp": "胸を押さえているところを見ると、あまりの緊張に胸が苦しいのかと思ってしまう。",
    "post_jp": "胸を押さえているところを見ると、あまりの緊張に胸が苦しいのかと思ってしまう。",
    "pre_zh": "看她捂着胸口的样子，应该是紧张过度导致胸口难受吧。",
    "proofread_zh": "",
    "trans_by": "sakura-009",
    "proofread_by": "",
    "post_zh_preview": "看她捂着胸口的样子，应该是紧张过度导致胸口难受吧。"
  },
  {
    "index": 62,
    "name": "セラ",
    "pre_jp": "「ザクール、アタシの言うことをちゃんと聞きなさいよ！　何かおかしいわね……どういうこと？」",
    "post_jp": "ザクール、アタシの言うことをちゃんと聞きなさいよ！　何かおかしいわね……どういうこと？",
    "pre_zh": "札库罗，你给我好好听话啊！感觉有点不对劲……怎么回事？",
    "proofread_zh": "",
    "trans_by": "sakura-009",
    "proofread_by": "",
    "post_zh_preview": "「札库罗，你给我好好听话啊！感觉有点不对劲……怎么回事？」"
  },
  {
    "index": 63,
    "name": "有紗",
    "pre_jp": "（やっぱり、おかしいと思ってるのは私だけじゃない。今なら逃げられるかも！）",
    "post_jp": "（やっぱり、おかしいと思ってるのは私だけじゃない。今なら逃げられるかも！）",
    "pre_zh": "（果然，觉得不对劲的不只是我。现在说不定能逃掉！）",
    "proofread_zh": "",
    "trans_by": "sakura-009",
    "proofread_by": "",
    "post_zh_preview": "（果然，觉得不对劲的不只是我。现在说不定能逃掉！）"
  },
  {
    "index": 64,
    "name": "有紗",
    "pre_jp": "「ユーリ、こっちよ！」",
    "post_jp": "尤莉、こっちよ！",
    "pre_zh": "尤莉，这边！",
    "proofread_zh": "",
    "trans_by": "sakura-009",
    "proofread_by": "",
    "post_zh_preview": "「尤莉，这边！」"
  },
  {
    "index": 65,
    "name": "ユーリ",
    "pre_jp": "「えっ、あっ……」",
    "post_jp": "えっ、あっ……",
    "pre_zh": "哎，啊……",
    "proofread_zh": "",
    "trans_by": "sakura-009",
    "proofread_by": "",
    "post_zh_preview": "「哎，啊……」"
  },
  {
    "index": 66,
    "name": "",
    "pre_jp": "有紗はユーリの手を握り締めて走り出した。",
    "post_jp": "有紗は尤莉の手を握り締めて走り出した。",
    "pre_zh": "有纱握着尤莉的手，飞奔起来。",
    "proofread_zh": "",
    "trans_by": "sakura-009",
    "proofread_by": "",
    "post_zh_preview": "有纱握着尤莉的手，飞奔起来。"
  },
  {
    "index": 67,
    "name": "",
    "pre_jp": "ユーリは背後で転びそうになるものの、なんとか体勢を立て直して追いかけてくる。",
    "post_jp": "尤莉は背後で転びそうになるものの、なんとか体勢を立て直して追いかけてくる。",
    "pre_zh": "尤莉在后面差点摔倒，但还是勉强站稳了脚跟，追了上来。",
    "proofread_zh": "",
    "trans_by": "sakura-009",
    "proofread_by": "",
    "post_zh_preview": "尤莉在后面差点摔倒，但还是勉强站稳了脚跟，追了上来。"
  },
  {
    "index": 68,
    "name": "",
    "pre_jp": "有紗はそれを確認してからスピードを上げた。",
    "post_jp": "有紗はそれを確認してからスピードを上げた。",
    "pre_zh": "有纱确认尤莉跟上之后，加快了速度。",
    "proofread_zh": "",
    "trans_by": "sakura-009",
    "proofread_by": "",
    "post_zh_preview": "有纱确认尤莉跟上之后，加快了速度。"
  },
  {
    "index": 69,
    "name": "有紗",
    "pre_jp": "「はぁっ、はぁっ……ここまで来れば大丈夫かな」",
    "post_jp": "はぁっ、はぁっ……ここまで来れば大丈夫かな",
    "pre_zh": "哈啊，哈啊……跑到这里应该就没事了吧",
    "proofread_zh": "",
    "trans_by": "sakura-009",
    "proofread_by": "",
    "post_zh_preview": "「哈啊，哈啊……跑到这里应该就没事了吧」"
  },
  {
    "index": 70,
    "name": "ユーリ",
    "pre_jp": "「うん……はぁっ、はぁっ……」",
    "post_jp": "うん……はぁっ、はぁっ……",
    "pre_zh": "嗯……哈啊，哈啊……",
    "proofread_zh": "",
    "trans_by": "sakura-009",
    "proofread_by": "",
    "post_zh_preview": "「嗯……哈啊，哈啊……」"
  },
  {
    "index": 71,
    "name": "",
    "pre_jp": "どこをどう走ったのか、途中から覚えていない。",
    "post_jp": "どこをどう走ったのか、途中から覚えていない。",
    "pre_zh": "途中发生了什么，她已经记不清了。",
    "proofread_zh": "",
    "trans_by": "sakura-009",
    "proofread_by": "",
    "post_zh_preview": "途中发生了什么，她已经记不清了。"
  },
  {
    "index": 72,
    "name": "",
    "pre_jp": "気づけば人気のない路地に走り込んでいて、今は召喚獣の声も聞こえてこない。",
    "post_jp": "気づけば人気のない路地に走り込んでいて、今は召喚獣の声も聞こえてこない。",
    "pre_zh": "回过神来，她们已经跑进了一条人迹罕至的小巷，听不到召唤兽的声音。",
    "proofread_zh": "",
    "trans_by": "sakura-009",
    "proofread_by": "",
    "post_zh_preview": "回过神来，她们已经跑进了一条人迹罕至的小巷，听不到召唤兽的声音。"
  },
  {
    "index": 73,
    "name": "",
    "pre_jp": "胸の感触からはそれほど離れていないが分かるものの、思ったより距離は離れていないようだ。",
    "post_jp": "胸の感触からはそれほど離れていないが分かるものの、思ったより距離は離れていないようだ。",
    "pre_zh": "虽然离胸口的触感并不远，但似乎比想象中要近。",
    "proofread_zh": "",
    "trans_by": "sakura-009",
    "proofread_by": "",
    "post_zh_preview": "虽然离胸口的触感并不远，但似乎比想象中要近。"
  },
  {
    "index": 74,
    "name": "有紗",
    "pre_jp": "「ユーリは危ないからここにいて」",
    "post_jp": "尤莉は危ないからここにいて",
    "pre_zh": "尤莉，你待在这里，很危险的",
    "proofread_zh": "",
    "trans_by": "sakura-009",
    "proofread_by": "",
    "post_zh_preview": "「尤莉，你待在这里，很危险的」"
  },
  {
    "index": 75,
    "name": "",
    "pre_jp": "有紗が立ち上がろうとすると、繋いだままの手がぎゅっと握られた。",
    "post_jp": "有紗が立ち上がろうとすると、繋いだままの手がぎゅっと握られた。",
    "pre_zh": "有纱刚准备站起来，尤莉就握紧了她的手。",
    "proofread_zh": "",
    "trans_by": "sakura-009",
    "proofread_by": "",
    "post_zh_preview": "有纱刚准备站起来，尤莉就握紧了她的手。"
  },
  {
    "index": 76,
    "name": "ユーリ",
    "pre_jp": "「どこに……行くの？」",
    "post_jp": "どこに……行くの？",
    "pre_zh": "你要去……哪里？",
    "proofread_zh": "",
    "trans_by": "sakura-009",
    "proofread_by": "",
    "post_zh_preview": "「你要去……哪里？」"
  },
  {
    "index": 77,
    "name": "有紗",
    "pre_jp": "「ちょっと様子を見てくるわ。ここなら多分安全だろうし」",
    "post_jp": "ちょっと様子を見てくるわ。ここなら多分安全だろうし",
    "pre_zh": "我去看看情况。这里应该很安全",
    "proofread_zh": "",
    "trans_by": "sakura-009",
    "proofread_by": "",
    "post_zh_preview": "「我去看看情况。这里应该很安全」"
  },
  {
    "index": 78,
    "name": "ユーリ",
    "pre_jp": "「だ、だめっ！　ありさはここにいて」",
    "post_jp": "だ、だめっ！　ありさはここにいて",
    "pre_zh": "不、不行！你待在这里",
    "proofread_zh": "",
    "trans_by": "sakura-009",
    "proofread_by": "",
    "post_zh_preview": "「不、不行！你待在这里」"
  },
  {
    "index": 79,
    "name": "有紗",
    "pre_jp": "「大丈夫、召喚獣に近づいたりしないから」",
    "post_jp": "大丈夫、召喚獣に近づいたりしないから",
    "pre_zh": "没事的，我不会靠近召唤兽的",
    "proofread_zh": "",
    "trans_by": "sakura-009",
    "proofread_by": "",
    "post_zh_preview": "「没事的，我不会靠近召唤兽的」"
  },
  {
    "index": 80,
    "name": "",
    "pre_jp": "ユーリは駄々をこねるように首を強く横に振った。",
    "post_jp": "尤莉は駄々をこねるように首を強く横に振った。",
    "pre_zh": "尤莉用力地摇了摇头，就像在闹别扭一样。",
    "proofread_zh": "",
    "trans_by": "sakura-009",
    "proofread_by": "",
    "post_zh_preview": "尤莉用力地摇了摇头，就像在闹别扭一样。"
  },
  {
    "index": 81,
    "name": "",
    "pre_jp": "震える手の感触が伝わってきて、有紗は手をふりほどけなくなってしまった。",
    "post_jp": "震える手の感触が伝わってきて、有紗は手をふりほどけなくなってしまった。",
    "pre_zh": "尤莉的手在颤抖，有纱不忍心甩开她的手。",
    "proofread_zh": "",
    "trans_by": "sakura-009",
    "proofread_by": "",
    "post_zh_preview": "尤莉的手在颤抖，有纱不忍心甩开她的手。"
  },
  {
    "index": 82,
    "name": "有紗",
    "pre_jp": "（どうしよう……ユーリが怖がるのも分かるけど、あのまま召喚獣を暴れさせておくわけにはいかないし）",
    "post_jp": "（どうしよう……尤莉が怖がるのも分かるけど、あのまま召喚獣を暴れさせておくわけにはいかないし）",
    "pre_zh": "（怎么办……虽然我也知道尤莉很害怕，但也不能放任召唤兽继续胡闹下去）",
    "proofread_zh": "",
    "trans_by": "sakura-009",
    "proofread_by": "",
    "post_zh_preview": "（怎么办……虽然我也知道尤莉很害怕，但也不能放任召唤兽继续胡闹下去）"
  },
  {
    "index": 83,
    "name": "",
    "pre_jp": "強く握り締めてくるユーリの手からは、怯えの色が強く感じられる。",
    "post_jp": "強く握り締めてくる尤莉の手からは、怯えの色が強く感じられる。",
    "pre_zh": "尤莉的手握得很紧，我能感受到她内心的恐惧。",
    "proofread_zh": "",
    "trans_by": "sakura-009",
    "proofread_by": "",
    "post_zh_preview": "尤莉的手握得很紧，我能感受到她内心的恐惧。"
  },
  {
    "index": 84,
    "name": "",
    "pre_jp": "有紗は一旦座ると、ユーリの肩をそっと抱きしめた。",
    "post_jp": "有紗は一旦座ると、尤莉の肩をそっと抱きしめた。",
    "pre_zh": "有纱坐了下来，轻轻搂住了尤莉的肩膀。",
    "proofread_zh": "",
    "trans_by": "sakura-009",
    "proofread_by": "",
    "post_zh_preview": "有纱坐了下来，轻轻搂住了尤莉的肩膀。"
  },
  {
    "index": 85,
    "name": "有紗",
    "pre_jp": "「大丈夫、側にいるから」",
    "post_jp": "大丈夫、側にいるから",
    "pre_zh": "没事的，我会陪在你身边",
    "proofread_zh": "",
    "trans_by": "sakura-009",
    "proofread_by": "",
    "post_zh_preview": "「没事的，我会陪在你身边」"
  },
  {
    "index": 86,
    "name": "ユーリ",
    "pre_jp": "「うん……」",
    "post_jp": "うん……",
    "pre_zh": "嗯……",
    "proofread_zh": "",
    "trans_by": "sakura-009",
    "proofread_by": "",
    "post_zh_preview": "「嗯……」"
  },
  {
    "index": 87,
    "name": "",
    "pre_jp": "とはいえ、いつまでもここにいるわけには行かない。",
    "post_jp": "とはいえ、いつまでもここにいるわけには行かない。",
    "pre_zh": "但是，我们也不能一直待在这里。",
    "proofread_zh": "",
    "trans_by": "sakura-009",
    "proofread_by": "",
    "post_zh_preview": "但是，我们也不能一直待在这里。"
  },
  {
    "index": 88,
    "name": "",
    "pre_jp": "有紗はユーリの手を握り締めながら、ここから脱出する方法を思案していた。",
    "post_jp": "有紗は尤莉の手を握り締めながら、ここから脱出する方法を思案していた。",
    "pre_zh": "有纱握着尤莉的手，思考着如何逃离这里。",
    "proofread_zh": "",
    "trans_by": "sakura-009",
    "proofread_by": "",
    "post_zh_preview": "有纱握着尤莉的手，思考着如何逃离这里。"
  }
]